{
  "folderUid": "fel522vsv8flsf",
  "uid": "adp4wua8l7itce",
  "name": "Monthly - Memory Usage (AVG)",
  "kind": 1,
  "type": "stat",
  "description": "",
  "model": {
    "datasource": {
      "type": "prometheus"
    },
    "description": "",
    "fieldConfig": {
      "defaults": {
        "color": {
          "mode": "thresholds"
        },
        "mappings": [],
        "max": 100,
        "min": 0,
        "thresholds": {
          "mode": "absolute",
          "steps": [
            {
              "color": "green",
              "value": null
            },
            {
              "color": "red",
              "value": 90
            }
          ]
        },
        "unit": "percent"
      },
      "overrides": []
    },
    "gridPos": {
      "h": 17,
      "w": 8,
      "x": 16,
      "y": 20
    },
    "id": 5,
    "interval": "30m",
    "options": {
      "colorMode": "value",
      "graphMode": "area",
      "justifyMode": "auto",
      "orientation": "auto",
      "percentChangeColorMode": "standard",
      "reduceOptions": {
        "calcs": [
          "lastNotNull"
        ],
        "fields": "",
        "values": false
      },
      "showPercentChange": false,
      "textMode": "auto",
      "wideLayout": true
    },
    "pluginVersion": "11.5.2",
    "targets": [
      {
        "datasource": {
          "type": "prometheus"
        },
        "editorMode": "code",
        "exemplar": false,
        "expr": "label_replace(\navg by (job) (100 * (1 - (avg_over_time(node_memory_MemAvailable_bytes{instance=~\"(scaler|interactive|automation|designer).*:9100\", instanceName=~\"$qmsCustomer-(?i:($qmsEnvironment))\"}[$__range]) / avg_over_time(node_memory_MemTotal_bytes{instance=~\"(scaler|interactive|automation|designer).*:9100\", instanceName=~\"$qmsCustomer-(?i:($qmsEnvironment))\"}[$__range])))),\n  \"instanceShort\", \"$1-$2\", \"job\", \"^[^-]*-(.*)-([^-]*)-[^-]*$\"\n)\n",
        "format": "time_series",
        "instant": true,
        "legendFormat": "Physical: {{instanceShort}}",
        "range": false,
        "refId": "Physical"
      }
    ],
    "title": "Memory Usage (AVG) $qmsEnvironment",
    "type": "stat"
  }
}