{
  "uid": "prometheus-internal-dashboard001",
  "title": "Prometheus Internal Metrics",
  "tags": ["prometheus", "internal"],
  "timezone": "browser",
  "schemaVersion": 30,
  "version": 1,
  "refresh": "30s",
  "panels": [
     {
  "gridPos": { "h": 8, "w": 12, "x": 12, "y": 0 },
  "id": 7,
  "title": "Node Forks Total",
  "type": "stat",
  "libraryPanel": {
    "name": "Node Forks Total",
    "uid": "auto-node-forks-total"
  }
},
   {
  "gridPos": { "h": 8, "w": 12, "x": 0, "y": 0 },
  "id": 3,
  "title": "Counter",
  "type": "stat",
  "libraryPanel": { "name": "Counter", "uid": "aez4o4a9vgxdse" }
},
    {
  "gridPos": {
    "h": 8,
    "w": 12,
    "x": 0,
    "y": 8
  },
  "id": 1,
  "title": "form",
  "type": "timeseries",
  "libraryPanel": {
    "name": "form",
    "uid": "aez4o4xqtmg3kf"
  }
},
        {
      "gridPos": {
        "h": 8,
        "w": 12,
        "x": 0,
        "y": 0
      },
      "id": 1,
      "libraryPanel": {
        "name": "Series",
        "uid": "bez4onojrzcaoc"
      },
      "title": "Series",
      "type": "library-panel-ref"
    },
    {
      "type": "stat",
      "title": "Query Log Enabled",
      "id": 1,
      "datasource": "prometheus",
      "targets": [
        {
          "expr": "node_memory_Inactive_bytes",
          "legendFormat": "Query Log",
          "refId": "A"
        }
      ],
      "options": {
        "reduceOptions": {
          "calcs": ["lastNotNull"],
          "fields": "",
          "values": false
        },
        "colorMode": "value",
        "graphMode": "none",
        "justifyMode": "center"
      }
    },
    {
      "type": "graph",
      "title": "Scrape Series Added",
      "id": 2,
      "datasource": "prometheus",
      "targets": [
        {
          "expr": "up",
          "legendFormat": "Series Added",
          "refId": "B"
        }
      ]
    }
  ]
}
